{
	"CompositeForms": {
	},
	"Entities": {
		"EN_CLIENTEIX_920": {
			"labels": [
			]
		},
		"EN_CUENTARZM_852": {
			"labels": [
			]
		}
	},
	"Forms": {
		"T_CNTASADQLTLAP_450": {
			"blis": [
			],
			"entities": {
				"EN_1RYFYHYJA_254": [
					"AT03_2DSRLIXG254"
				],
				"EN_CLIENTEIX_920": [
					"AT30_NOMBREIQ920",
					"AT59_APELLIDD920",
					"AT91_CEDULAKS920",
					"AT94_CODIGOTA920"
				]
			},
			"externalEntities": {
			},
			"externalQueries": {
			},
			"header": [
			],
			"labels": [
				"LBL_CNTAS_CEDULAWXJ_29913"
			],
			"queries": {
				"Q_CLIETNNT_ZN50": [
					"QM_CLIET5T0N0274_02",
					"QM_CLIETTNT5T907_03",
					"QM_CLIETTTT00309_04",
					"QM_CLIETZNZN5678_01"
				]
			},
			"subForms": [
			]
		},
		"T_CNTASIQOTREKI_837": {
			"blis": [
			],
			"entities": {
			},
			"externalEntities": {
			},
			"externalQueries": {
			},
			"header": [
			],
			"labels": [
			],
			"queries": {
			},
			"subForms": [
			]
		},
		"T_CNTASPIVDVWDH_706": {
			"blis": [
			],
			"entities": {
			},
			"externalEntities": {
			},
			"externalQueries": {
			},
			"header": [
			],
			"labels": [
			],
			"queries": {
			},
			"subForms": [
			]
		},
		"T_CNTASTCBBKEXW_758": {
			"blis": [
			],
			"entities": {
				"EN_2UYHOXGPS_976": [
					"AT02_1WBNTPEV976"
				],
				"EN_3QMTKISDC_617": [
					"AT02_1PDMJEAM617"
				],
				"EN_CUENTARZM_852": [
					"AT64_SALDOZTR852",
					"AT67_TIPOCUET852",
					"AT68_CEDULAEL852",
					"AT73_NOMBRENN852",
					"AT75_NUMEROCN852",
					"AT93_APELLIDE852"
				]
			},
			"externalEntities": {
			},
			"externalQueries": {
			},
			"header": [
			],
			"labels": [
				"LBL_CNTAS_CUENTADOT_52317",
				"LBL_CNTAS_CUENTAOEE_37869"
			],
			"queries": {
				"Q_CUENTAAT_QZ46": [
					"QM_CUENT6TA4T502_01",
					"QM_CUENTAA4AT507_05",
					"QM_CUENTAA64A176_04",
					"QM_CUENTTZQQT279_06",
					"QM_CUENTZAZQT267_03",
					"QM_CUENTZQT4Q823_02"
				]
			},
			"subForms": [
			]
		},
		"T_CNTASYADRIJAP_499": {
			"blis": [
			],
			"entities": {
			},
			"externalEntities": {
			},
			"externalQueries": {
			},
			"header": [
			],
			"labels": [
			],
			"queries": {
			},
			"subForms": [
			]
		}
	},
	"Queries": {
		"Q_CLIETNNT_ZN50": {
			"labels": [
			]
		},
		"Q_CUENTAAT_QZ46": {
			"labels": [
			]
		}
	}
}
